<edmx:Edmx xmlns:edmx="http://docs.oasis-open.org/odata/ns/edmx" Version="4.0">
	<edmx:Reference Uri="/sap/opu/odata/mhp/SMART_MSS_REPO_SRV/$metadata">
		<edmx:Include Alias="Metadata" Namespace="MHP.SMART_MSS_REPO_SRV"/>
	</edmx:Reference>
	<edmx:Reference Uri="https://wiki.scn.sap.com/wiki/download/attachments/448470968/UI.xml?api=v2">
		<edmx:Include Alias="UI" Namespace="com.sap.vocabularies.UI.v1"/>
	</edmx:Reference>
	<edmx:Reference Uri="https://wiki.scn.sap.com/wiki/download/attachments/448470974/Common.xml?api=v2">
		<edmx:Include Alias="Common" Namespace="com.sap.vocabularies.Common.v1"/>
	</edmx:Reference>
	<edmx:DataServices>
		<Schema xmlns="http://docs.oasis-open.org/odata/ns/edm" Namespace="mhpintegrationcockpit.annotations.annotation.MHP.SMART_MSS_REPO_SRV">
			<Annotations Target="Metadata.INTCENTER">
				<Annotation Term="UI.DataPoint" Qualifier="VisualFilterByStream">
					<Record Type="UI.DataPointType">
						<PropertyValue Property="Value" Path="COUNTER_MSG"/>
					</Record>
				</Annotation>
				<Annotation Term="UI.DataPoint" Qualifier="VisualFilterByTYPE">
					<Record Type="UI.DataPointType">
						<PropertyValue Property="Value" Path="COUNTER_MSG"/>
						<PropertyValue Property="Criticality" Path="CRITICALITY_4_TYPE"/>
					</Record>
				</Annotation>
				<Annotation Term="UI.DataPoint" Qualifier="VisualFilterBySTATUS">
					<Record Type="UI.DataPointType">
						<PropertyValue Property="Value" Path="COUNTER_MSG"/>
						<PropertyValue Property="Criticality" Path="CRITICALITY_4_STATUS"/>
					</Record>
				</Annotation>
				<Annotation Term="UI.DataPoint" Qualifier="SachXKPI">
					<Record Type="UI.DataPointType">
						<PropertyValue Property="Value" Path="COUNTER_MSG"/>
						<PropertyValue Property="Criticality" EnumMember="UI.CriticalityType/Negative"/>
						<PropertyValue Property="Title" String="{@i18n&gt;kpiPersonResponsible}"/>
					</Record>
				</Annotation>
				<Annotation Term="UI.KPI" Qualifier="SachXKPI">
					<Record Type="UI.KPIType">
						<PropertyValue Property="SelectionVariant" Path="@UI.SelectionVariant#SachXKPI"/>
						<PropertyValue Property="DataPoint" Path="@UI.DataPoint#SachXKPI"/>
						<PropertyValue Property="ID" String="MainContentAreaSachXKPI"/>
						<PropertyValue Property="Detail">
							<Record Type="UI.KPIDetailType">
								<PropertyValue Property="DefaultPresentationVariant" Path="@UI.PresentationVariant#SachXKPI"/>
							</Record>
						</PropertyValue>
					</Record>
				</Annotation>
				<Annotation Term="UI.Chart" Qualifier="SachXKPI">
					<Record Type="UI.ChartDefinitionType">
						<PropertyValue Property="ChartType" EnumMember="UI.ChartType/Donut"/>
						<PropertyValue Property="Measures">
							<Collection>
								<PropertyPath>COUNTER_MSG</PropertyPath>
							</Collection>
						</PropertyValue>
						<PropertyValue Property="MeasureAttributes">
							<Collection>
								<Record Type="UI.ChartMeasureAttributeType">
									<PropertyValue Property="Measure" PropertyPath="COUNTER_MSG"/>
									<PropertyValue Property="Role" EnumMember="UI.ChartMeasureRoleType/Axis1"/>
								</Record>
							</Collection>
						</PropertyValue>
						<PropertyValue Property="Dimensions">
							<Collection>
								<PropertyPath>SACHB_SBGRPCODE</PropertyPath>
							</Collection>
						</PropertyValue>
						<PropertyValue Property="DimensionAttributes">
							<Collection>
								<Record Type="UI.ChartDimensionAttributeType">
									<PropertyValue Property="Role" EnumMember="UI.ChartDimensionRoleType/Category"/>
									<PropertyValue Property="Dimension" PropertyPath="SACHB_SBGRPCODE"/>
								</Record>
							</Collection>
						</PropertyValue>
					</Record>
				</Annotation>
				<Annotation Term="UI.PresentationVariant" Qualifier="SachXKPI">
					<Record Type="UI.PresentationVariantType">
						<PropertyValue Property="Text" String="{@i18n&gt;kpiPersonResponsible}"/>
						<PropertyValue Property="Visualizations">
							<Collection>
								<AnnotationPath>@UI.Chart#SachXKPI</AnnotationPath>
								<AnnotationPath>@UI.DataPoint#SachXKPI</AnnotationPath>
							</Collection>
						</PropertyValue>
					</Record>
				</Annotation>
				<Annotation Term="UI.SelectionVariant" Qualifier="SachXKPI">
					<Record Type="UI.SelectionVariantType">
						<PropertyValue Property="Text" String="{@i18n&gt;kpiPersonResponsible}"/>
					</Record>
				</Annotation>
				<Annotation Term="UI.SelectionPresentationVariant" Qualifier="SachXKPI">
					<Record Type="UI.SelectionPresentationVariantType">
						<PropertyValue Property="SelectionVariant" Path="@UI.SelectionVariant#SachXKPI"/>
						<PropertyValue Property="PresentationVariant" Path="@UI.PresentationVariant#SachXKPI"/>
					</Record>
				</Annotation>
				<Annotation Term="UI.Chart" Qualifier="VisualFilterByStream">
					<Record Type="UI.ChartDefinitionType">
						<PropertyValue Property="ChartType" EnumMember="UI.ChartType/Donut"/>
						<PropertyValue Property="Measures">
							<Collection>
								<PropertyPath>COUNTER_MSG</PropertyPath>
							</Collection>
						</PropertyValue>
						<PropertyValue Property="MeasureAttributes">
							<Collection>
								<Record Type="UI.ChartMeasureAttributeType">
									<PropertyValue Property="Measure" PropertyPath="COUNTER_MSG"/>
									<PropertyValue Property="Role" EnumMember="UI.ChartMeasureRoleType/Axis1"/>
									<PropertyValue Property="DataPoint" AnnotationPath="@UI.DataPoint#VisualFilterByStream"/>
								</Record>
							</Collection>
						</PropertyValue>
						<PropertyValue Property="Dimensions">
							<Collection>
								<PropertyPath>STREAM_DIRECTION</PropertyPath>
							</Collection>
						</PropertyValue>
						<PropertyValue Property="DimensionAttributes">
							<Collection>
								<Record Type="UI.ChartDimensionAttributeType">
									<PropertyValue Property="Role" EnumMember="UI.ChartDimensionRoleType/Category"/>
									<PropertyValue Property="Dimension" PropertyPath="STREAM_DIRECTION"/>
								</Record>
							</Collection>
						</PropertyValue>
					</Record>
				</Annotation>
				<Annotation Term="UI.PresentationVariant" Qualifier="VisualFilterByStream">
					<Record Type="UI.PresentationVariantType">
						<PropertyValue Property="Visualizations">
							<Collection>
								<AnnotationPath>@UI.Chart#VisualFilterByStream</AnnotationPath>
							</Collection>
						</PropertyValue>
					</Record>
				</Annotation>
				<Annotation Term="UI.Chart" Qualifier="VisualFilterByCWEEK">
					<Record Type="UI.ChartDefinitionType">
						<PropertyValue Property="ChartType" EnumMember="UI.ChartType/Line"/>
						<PropertyValue Property="Measures">
							<Collection>
								<PropertyPath>COUNTER_MSG</PropertyPath>
							</Collection>
						</PropertyValue>
						<PropertyValue Property="MeasureAttributes">
							<Collection>
								<Record Type="UI.ChartMeasureAttributeType">
									<PropertyValue Property="Measure" PropertyPath="COUNTER_MSG"/>
									<PropertyValue Property="Role" EnumMember="UI.ChartMeasureRoleType/Axis1"/>
								</Record>
							</Collection>
						</PropertyValue>
						<PropertyValue Property="Dimensions">
							<Collection>
								<PropertyPath>VIS_DATE_CWEEK</PropertyPath>
							</Collection>
						</PropertyValue>
						<PropertyValue Property="DimensionAttributes">
							<Collection>
								<Record Type="UI.ChartDimensionAttributeType">
									<PropertyValue Property="Role" EnumMember="UI.ChartDimensionRoleType/Category"/>
									<PropertyValue Property="Dimension" PropertyPath="VIS_DATE_CWEEK"/>
								</Record>
							</Collection>
						</PropertyValue>
					</Record>
				</Annotation>
				<Annotation Term="UI.PresentationVariant" Qualifier="VisualFilterByCWEEK">
					<Record Type="UI.PresentationVariantType">
						<PropertyValue Property="Visualizations">
							<Collection>
								<AnnotationPath>@UI.Chart#VisualFilterByCWEEK</AnnotationPath>
							</Collection>
						</PropertyValue>
					</Record>
				</Annotation>
				<Annotation Term="UI.Chart" Qualifier="VisualFilterByTYPE">
					<Record Type="UI.ChartDefinitionType">
						<PropertyValue Property="ChartType" EnumMember="UI.ChartType/Donut"/>
						<PropertyValue Property="Measures">
							<Collection>
								<PropertyPath>COUNTER_MSG</PropertyPath>
							</Collection>
						</PropertyValue>
						<PropertyValue Property="MeasureAttributes">
							<Collection>
								<Record Type="UI.ChartMeasureAttributeType">
									<PropertyValue Property="Measure" PropertyPath="COUNTER_MSG"/>
									<PropertyValue Property="Role" EnumMember="UI.ChartMeasureRoleType/Axis1"/>
									<PropertyValue Property="DataPoint" AnnotationPath="@UI.DataPoint#VisualFilterByTYPE"/>
								</Record>
							</Collection>
						</PropertyValue>
						<PropertyValue Property="Dimensions">
							<Collection>
								<PropertyPath>MSG_TYPE</PropertyPath>
							</Collection>
						</PropertyValue>
						<PropertyValue Property="DimensionAttributes">
							<Collection>
								<Record Type="UI.ChartDimensionAttributeType">
									<PropertyValue Property="Role" EnumMember="UI.ChartDimensionRoleType/Category"/>
									<PropertyValue Property="Dimension" PropertyPath="MSG_TYPE"/>
								</Record>
							</Collection>
						</PropertyValue>
					</Record>
				</Annotation>
				<Annotation Term="UI.PresentationVariant" Qualifier="VisualFilterByTYPE">
					<Record Type="UI.PresentationVariantType">
						<PropertyValue Property="Visualizations">
							<Collection>
								<AnnotationPath>@UI.Chart#VisualFilterByTYPE</AnnotationPath>
							</Collection>
						</PropertyValue>
					</Record>
				</Annotation>
				<Annotation Term="UI.Chart" Qualifier="VisualFilterBySTATUS">
					<Record Type="UI.ChartDefinitionType">
						<PropertyValue Property="ChartType" EnumMember="UI.ChartType/Donut"/>
						<PropertyValue Property="Measures">
							<Collection>
								<PropertyPath>COUNTER_MSG</PropertyPath>
							</Collection>
						</PropertyValue>
						<PropertyValue Property="MeasureAttributes">
							<Collection>
								<Record Type="UI.ChartMeasureAttributeType">
									<PropertyValue Property="Measure" PropertyPath="COUNTER_MSG"/>
									<PropertyValue Property="Role" EnumMember="UI.ChartMeasureRoleType/Axis1"/>
									<PropertyValue Property="DataPoint" AnnotationPath="@UI.DataPoint#VisualFilterBySTATUS"/>
								</Record>
							</Collection>
						</PropertyValue>
						<PropertyValue Property="Dimensions">
							<Collection>
								<PropertyPath>STATUS</PropertyPath>
							</Collection>
						</PropertyValue>
						<PropertyValue Property="DimensionAttributes">
							<Collection>
								<Record Type="UI.ChartDimensionAttributeType">
									<PropertyValue Property="Role" EnumMember="UI.ChartDimensionRoleType/Category"/>
									<PropertyValue Property="Dimension" PropertyPath="STATUS"/>
								</Record>
							</Collection>
						</PropertyValue>
					</Record>
				</Annotation>
				<Annotation Term="UI.PresentationVariant" Qualifier="VisualFilterBySTATUS">
					<Record Type="UI.PresentationVariantType">
						<PropertyValue Property="Visualizations">
							<Collection>
								<AnnotationPath>@UI.Chart#VisualFilterBySTATUS</AnnotationPath>
							</Collection>
						</PropertyValue>
					</Record>
				</Annotation>
				<Annotation Term="UI.Chart" Qualifier="VisualFilterByOTYPE">
					<Record Type="UI.ChartDefinitionType">
						<PropertyValue Property="ChartType" EnumMember="UI.ChartType/Donut"/>
						<PropertyValue Property="Measures">
							<Collection>
								<PropertyPath>COUNTER_MSG</PropertyPath>
							</Collection>
						</PropertyValue>
						<PropertyValue Property="MeasureAttributes">
							<Collection>
								<Record Type="UI.ChartMeasureAttributeType">
									<PropertyValue Property="Measure" PropertyPath="COUNTER_MSG"/>
									<PropertyValue Property="Role" EnumMember="UI.ChartMeasureRoleType/Axis1"/>
								</Record>
							</Collection>
						</PropertyValue>
						<PropertyValue Property="Dimensions">
							<Collection>
								<PropertyPath>OTYPE</PropertyPath>
							</Collection>
						</PropertyValue>
						<PropertyValue Property="DimensionAttributes">
							<Collection>
								<Record Type="UI.ChartDimensionAttributeType">
									<PropertyValue Property="Role" EnumMember="UI.ChartDimensionRoleType/Category"/>
									<PropertyValue Property="Dimension" PropertyPath="OTYPE"/>
								</Record>
							</Collection>
						</PropertyValue>
					</Record>
				</Annotation>
				<Annotation Term="UI.PresentationVariant" Qualifier="VisualFilterByOTYPE">
					<Record Type="UI.PresentationVariantType">
						<PropertyValue Property="Visualizations">
							<Collection>
								<AnnotationPath>@UI.Chart#VisualFilterByOTYPE</AnnotationPath>
							</Collection>
						</PropertyValue>
					</Record>
				</Annotation>
				<Annotation Term="UI.Chart" Qualifier="VisualFilterByMSGIDNUM">
					<Record Type="UI.ChartDefinitionType">
						<PropertyValue Property="ChartType" EnumMember="UI.ChartType/Bar"/>
						<PropertyValue Property="Measures">
							<Collection>
								<PropertyPath>COUNTER_MSG</PropertyPath>
							</Collection>
						</PropertyValue>
						<PropertyValue Property="MeasureAttributes">
							<Collection>
								<Record Type="UI.ChartMeasureAttributeType">
									<PropertyValue Property="Measure" PropertyPath="COUNTER_MSG"/>
									<PropertyValue Property="Role" EnumMember="UI.ChartMeasureRoleType/Axis1"/>
								</Record>
							</Collection>
						</PropertyValue>
						<PropertyValue Property="Dimensions">
							<Collection>
								<PropertyPath>MSG_IDNUM</PropertyPath>
							</Collection>
						</PropertyValue>
						<PropertyValue Property="DimensionAttributes">
							<Collection>
								<Record Type="UI.ChartDimensionAttributeType">
									<PropertyValue Property="Role" EnumMember="UI.ChartDimensionRoleType/Category"/>
									<PropertyValue Property="Dimension" PropertyPath="MSG_IDNUM"/>
								</Record>
							</Collection>
						</PropertyValue>
					</Record>
				</Annotation>
				<Annotation Term="UI.PresentationVariant" Qualifier="VisualFilterByMSGIDNUM">
					<Record Type="UI.PresentationVariantType">
						<PropertyValue Property="Visualizations">
							<Collection>
								<AnnotationPath>@UI.Chart#VisualFilterByMSGIDNUM</AnnotationPath>
							</Collection>
						</PropertyValue>
					</Record>
				</Annotation>
				<Annotation Term="UI.SelectionFields">
					<Collection>
						<PropertyPath>STATUS</PropertyPath>
						<PropertyPath>VIS_DATE_CWEEK</PropertyPath>
						<PropertyPath>OTYPE</PropertyPath>
						<PropertyPath>MSG_TYPE</PropertyPath>
						<PropertyPath>MSG_IDNUM</PropertyPath>
						<PropertyPath>STREAM_DIRECTION</PropertyPath>
					</Collection>
				</Annotation>
				<Annotation Term="UI.Chart" Qualifier="ContentAreaChart">
					<Record Type="UI.ChartDefinitionType">
						<PropertyValue Property="ChartType" EnumMember="UI.ChartType/ColumnStacked"/>
						<PropertyValue Property="MeasureAttributes">
							<Collection>
								<Record Type="UI.ChartMeasureAttributeType">
									<PropertyValue Property="Measure" PropertyPath="COUNTER_MSG"/>
									<PropertyValue Property="Role" EnumMember="UI.ChartMeasureRoleType/Axis1"/>
									<PropertyValue Property="DataPoint" AnnotationPath="@UI.DataPoint#VisualFilterBySTATUS"/>
								</Record>
							</Collection>
						</PropertyValue>
						<PropertyValue Property="Measures">
							<Collection>
								<PropertyPath>COUNTER_MSG</PropertyPath>
							</Collection>
						</PropertyValue>
						<PropertyValue Property="DimensionAttributes">
							<Collection>
								<Record Type="UI.ChartDimensionAttributeType">
									<PropertyValue Property="Dimension" PropertyPath="RUN_DATE"/>
									<PropertyValue Property="Role" EnumMember="UI.ChartDimensionRoleType/Category"/>
								</Record>
								<Record Type="UI.ChartDimensionAttributeType">
									<PropertyValue Property="Dimension" PropertyPath="STATUS"/>
									<PropertyValue Property="Role" EnumMember="UI.ChartDimensionRoleType/Series"/>
								</Record>
							</Collection>
						</PropertyValue>
						<PropertyValue Property="Dimensions">
							<Collection>
								<PropertyPath>RUN_DATE</PropertyPath>
								<PropertyPath>STATUS</PropertyPath>
							</Collection>
						</PropertyValue>
					</Record>
				</Annotation>
				<Annotation Term="UI.LineItem" Qualifier="ContentAreaTable">
					<Collection>
						<Record Type="UI.DataField">
							<PropertyValue Property="Value" Path="INT_RUN"/>
						</Record>
						<Record Type="UI.DataField">
							<PropertyValue Property="Value" Path="MOLGA"/>
						</Record>
						<Record Type="UI.DataField">
							<PropertyValue Property="Value" Path="OTYPE"/>
						</Record>
						<Record Type="UI.DataField">
							<PropertyValue Property="Value" Path="SAP_ID"/>
						</Record>
						<Record Type="UI.DataField">
							<PropertyValue Property="Value" Path="CLOUD_ID"/>
						</Record>
						<Record Type="UI.DataField">
							<PropertyValue Property="Value" Path="COUNTER_MSG"/>
						</Record>
						<Record Type="UI.DataField">
							<PropertyValue Property="Value" Path="STATUS"/>
						</Record>
					</Collection>
					<Annotation Term="UI.Criticality" Path="CRITICALITY_4_STATUS"/>
				</Annotation>
				<Annotation Term="UI.PresentationVariant" Qualifier="MainContentArea">
					<Record Type="UI.PresentationVariantType">
						<PropertyValue Property="Visualizations">
							<Collection>
								<AnnotationPath>@UI.Chart#ContentAreaChart</AnnotationPath>
								<AnnotationPath>@UI.LineItem#ContentAreaTable</AnnotationPath>
							</Collection>
						</PropertyValue>
						<PropertyValue Property="SortOrder">
							<Collection>
								<Record Type="Common.SortOrderType">
									<PropertyValue Property="Property" PropertyPath="AEDTM"/>
									<PropertyValue Property="Descending" Bool="false"/>
								</Record>
							</Collection>
						</PropertyValue>
					</Record>
				</Annotation>
				<Annotation Term="UI.SelectionVariant" Qualifier="MainContentArea">
					<Record Type="UI.SelectionVariantType"/>
				</Annotation>
				<Annotation Term="UI.SelectionPresentationVariant" Qualifier="MainContentArea">
					<Record Type="UI.SelectionPresentationVariantType">
						<PropertyValue Property="SelectionVariant" Path="@UI.SelectionVariant#MainContentArea"/>
						<PropertyValue Property="PresentationVariant" Path="@UI.PresentationVariant#MainContentArea"/>
					</Record>
				</Annotation>
			</Annotations>
			<Annotations Target="Metadata.INTCENTER/STATUS">
				<Annotation Term="Common.FilterDefaultValue" String="03"/>
				<Annotation Term="Common.ValueList" Qualifier="VisualFilter">
					<Record Type="Common.ValueListType">
						<PropertyValue Property="CollectionPath" String="DV_INTCENTER"/>
						<PropertyValue Property="PresentationVariantQualifier" String="VisualFilterBySTATUS"/>
					</Record>
				</Annotation>
			</Annotations>
			<Annotations Target="Metadata.INTCENTER/MSG_TYPE">
				<Annotation Term="Common.ValueList" Qualifier="VisualFilter">
					<Record Type="Common.ValueListType">
						<PropertyValue Property="CollectionPath" String="DV_INTCENTER"/>
						<PropertyValue Property="PresentationVariantQualifier" String="VisualFilterByTYPE"/>
					</Record>
				</Annotation>
			</Annotations>
			<Annotations Target="Metadata.INTCENTER/OTYPE">
				<Annotation Term="Common.ValueList" Qualifier="VisualFilter">
					<Record Type="Common.ValueListType">
						<PropertyValue Property="CollectionPath" String="DV_INTCENTER"/>
						<PropertyValue Property="PresentationVariantQualifier" String="VisualFilterByOTYPE"/>
					</Record>
				</Annotation>
			</Annotations>
			<Annotations Target="Metadata.INTCENTER/MSG_IDNUM">
				<Annotation Term="Common.ValueList" Qualifier="VisualFilter">
					<Record Type="Common.ValueListType">
						<PropertyValue Property="CollectionPath" String="DV_INTCENTER"/>
						<PropertyValue Property="PresentationVariantQualifier" String="VisualFilterByMSGIDNUM"/>
					</Record>
				</Annotation>
			</Annotations>
			<Annotations Target="Metadata.INTCENTER/VIS_DATE_CWEEK">
				<Annotation Term="Common.ValueList" Qualifier="VisualFilter">
					<Record Type="Common.ValueListType">
						<PropertyValue Property="CollectionPath" String="DV_INTCENTER"/>
						<PropertyValue Property="PresentationVariantQualifier" String="VisualFilterByCWEEK"/>
					</Record>
				</Annotation>
			</Annotations>
			<Annotations Target="Metadata.INTCENTER/STREAM_DIRECTION">
				<Annotation Term="Common.ValueList" Qualifier="VisualFilter">
					<Record Type="Common.ValueListType">
						<PropertyValue Property="CollectionPath" String="DV_INTCENTER"/>
						<PropertyValue Property="PresentationVariantQualifier" String="VisualFilterByStream"/>
					</Record>
				</Annotation>
			</Annotations>
		</Schema>
	</edmx:DataServices>
</edmx:Edmx>
